LICENSE
README.md
setup.cfg
setup.py
neurochat/__init__.py
neurochat/nc_base.py
neurochat/nc_circular.py
neurochat/nc_clust.py
neurochat/nc_config.py
neurochat/nc_containeranalysis.py
neurochat/nc_control.py
neurochat/nc_data.py
neurochat/nc_datacontainer.py
neurochat/nc_defaults.py
neurochat/nc_event.py
neurochat/nc_hdf.py
neurochat/nc_lfp.py
neurochat/nc_plot.py
neurochat/nc_spatial.py
neurochat/nc_spike.py
neurochat/nc_ui.py
neurochat/nc_uigetfiles.py
neurochat/nc_uimerge.py
neurochat/nc_uiutils.py
neurochat/nc_utils.py
neurochat.egg-info/PKG-INFO
neurochat.egg-info/SOURCES.txt
neurochat.egg-info/dependency_links.txt
neurochat.egg-info/requires.txt
neurochat.egg-info/top_level.txt
neurochat_gui/__init__.py
neurochat_gui/neurochat_ui.py