Metadata-Version: 2.1
Name: neurochat
Version: 1.1.1a0
Summary: NeuroChaT: Neuron Characterisation Toolbox
Home-page: https://github.com/seankmartin/NeuroChaT
Author: Md Nurul Islam and Sean Martin
Author-email: martins7@tcd.ie
Maintainer: Md Nurul Islam and Sean Martin
Maintainer-email: martins7@tcd.ie
License: UNKNOWN
Download-URL: https://github.com/seankmartin/NeuroChaT/archive/v1.1.1a0.tar.gz
Platform: UNKNOWN
Classifier: Intended Audience :: Science/Research
Classifier: Topic :: Scientific/Engineering :: Mathematics
Classifier: Programming Language :: Python :: 3.6
Classifier: Programming Language :: Python :: 3.7
Classifier: Programming Language :: Python :: 3.8
Classifier: Operating System :: POSIX
Classifier: Operating System :: Unix
Classifier: Operating System :: Microsoft :: Windows
Classifier: License :: OSI Approved :: GNU General Public License v3 (GPLv3)
